aioworkers_databases/__init__.py
aioworkers_databases/database.py
aioworkers_databases-0.1.1.dist-info/LICENSE
aioworkers_databases-0.1.1.dist-info/WHEEL
aioworkers_databases-0.1.1.dist-info/METADATA
aioworkers_databases-0.1.1.dist-info/RECORD
