Metadata-Version: 2.1
Name: aioworkers-databases
Version: 0.1.1
Summary: Databases plugin for aioworkers
Home-page: https://github.com/aioworkers/aioworkers-databases
License: Apache Software License 2.0
Author: Alexander Bogushov
Author-email: abogushov@gmail.com
Requires-Python: >=3.6.1,<4.0
Classifier: Development Status :: 2 - Pre-Alpha
Classifier: Intended Audience :: Developers
Classifier: License :: OSI Approved :: Apache Software License
Classifier: License :: Other/Proprietary License
Classifier: Programming Language :: Python :: 3
Classifier: Programming Language :: Python :: 3.7
Classifier: Programming Language :: Python :: 3.8
Classifier: Programming Language :: Python :: 3.9
Requires-Dist: aioworkers (>=0.18,<0.19)
Requires-Dist: databases (>=0.4.0,<0.5.0)
Project-URL: Repository, https://github.com/aioworkers/aioworkers-databases
